AUTHORS
ChangeLog
LICENSE
Makefile
Pipfile
Pipfile.lock
README.md
requirements.txt
setup.cfg
setup.py
wolkenbrot.spec
docs/demo.gif
examples/openstack.json
examples/short.json
examples/template/Makefile
examples/template/template.json
examples/upload/bar.txt
examples/upload/foo.txt
tests/test_aws.py
wolkenbrot/__init__.py
wolkenbrot/aws.py
wolkenbrot/cli.py
wolkenbrot/common.py
wolkenbrot/os.py
wolkenbrot/util.py
wolkenbrot.egg-info/PKG-INFO
wolkenbrot.egg-info/SOURCES.txt
wolkenbrot.egg-info/dependency_links.txt
wolkenbrot.egg-info/entry_points.txt
wolkenbrot.egg-info/not-zip-safe
wolkenbrot.egg-info/pbr.json
wolkenbrot.egg-info/requires.txt
wolkenbrot.egg-info/top_level.txt