Metadata-Version: 2.1
Name: wolkenbrot
Version: 0.3.0
Summary: Create and Manage AWS EC2 AMI cloud images
Home-page: https://github.com/oz123/wolkenbrot
Author: Oz N Tiram
Author-email: oz.tiram@gmail.com
License: MIT
Platform: UNKNOWN
Classifier: Development Status :: 3 - Alpha
Classifier: Programming Language :: Python
Classifier: Intended Audience :: Developers
Classifier: Intended Audience :: System Administrators
Classifier: License :: OSI Approved :: MIT License
Classifier: Operating System :: OS Independent
Classifier: Topic :: Software Development
Provides-Extra: dev
Provides-Extra: openstack
